translate_json/__init__.py
translate_json/console.py
translate_json/main.py
translate_json/translate.py
translate_json/utils.py
translate_json-0.0.2.data/scripts/translate-json.py
translate_json-0.0.2.dist-info/LICENSE
translate_json-0.0.2.dist-info/METADATA
translate_json-0.0.2.dist-info/WHEEL
translate_json-0.0.2.dist-info/top_level.txt
translate_json-0.0.2.dist-info/RECORD
