Metadata-Version: 2.1
Name: translate-json
Version: 0.0.2
Summary: This is a command line tool to translate all string values in a JSON file to multiple languages using the Google Cloud Translate API.
Home-page: https://github.com/yxor/translate-json
Author: Ahmed Tounsi
Author-email: ahmeddottounsi@gmail.com
License: UNKNOWN
Project-URL: Bug Tracker, https://github.com/yxor/translate-json/issues
Platform: UNKNOWN
Classifier: Programming Language :: Python :: 3
Classifier: License :: OSI Approved :: MIT License
Classifier: Operating System :: OS Independent
Requires-Python: >=3.9
License-File: LICENSE
Requires-Dist: certifi (==2021.5.30)
Requires-Dist: python-dotenv (==0.19.0)
Requires-Dist: requests (==2.26.0)
Requires-Dist: urllib3 (==1.26.6) ; python_version >= "2.7" and python_version not in "3.0, 3.1, 3.2, 3.3, 3.4" and python_version < "4"
Requires-Dist: charset-normalizer (==2.0.4) ; python_version >= "3"
Requires-Dist: idna (==3.2) ; python_version >= "3"
